{
  "source": "arxiv_list_pastweek_html",
  "category": "cs.CV",
  "announcement_date": "2026-03-26",
  "fetched_at": "2026-03-29T07:58:46Z",
  "count": 135,
  "entries": [
    {
      "paper_id": "2603.24584",
      "abs_url": "https://arxiv.org/abs/2603.24584",
      "source_category": "cs.CV",
      "title": "TAG: Target-Agnostic Guidance for Stable Object-Centric Inference in Vision-Language-Action Models",
      "authors": [
        "Jiaying Zhou",
        "Zhihao Zhan",
        "Ruifeng Zhai",
        "Qinhan Lyu",
        "Hao Liu",
        "Keze Wang",
        "Liang Lin",
        "Guangrun Wang"
      ],
      "primary_subject": "Computer Vision and Pattern Recognition (cs.CV)",
      "subject_categories": [
        "cs.CV",
        "cs.RO"
      ],
      "announcement_date": "2026-03-26"
    },
    {
      "paper_id": "2603.24581",
      "abs_url": "https://arxiv.org/abs/2603.24581",
      "source_category": "cs.CV",
      "title": "Latent-WAM: Latent World Action Modeling for End-to-End Autonomous Driving",
      "authors": [
        "Linbo Wang",
        "Yupeng Zheng",
        "Qiang Chen",
        "Shiwei Li",
        "Yichen Zhang",
        "Zebin Xing",
        "Qichao Zhang",
        "Xiang Li",
        "Deheng Qian",
        "Pengxuan Yang",
        "Yihang Dong",
        "Ce Hao",
        "Xiaoqing Ye",
        "Junyu han",
        "Yifeng Pan",
        "Dongbin Zhao"
      ],
      "primary_subject": "Computer Vision and Pattern Recognition (cs.CV)",
      "subject_categories": [
        "cs.CV",
        "cs.RO"
      ],
      "announcement_date": "2026-03-26"
    },
    {
      "paper_id": "2603.24578",
      "abs_url": "https://arxiv.org/abs/2603.24578",
      "source_category": "cs.CV",
      "title": "Vision-Language Models vs Human: Perceptual Image Quality Assessment",
      "authors": [
        "Imran Mehmood",
        "Imad Ali Shah",
        "Ming Ronnier Luo",
        "Brian Deegan"
      ],
      "primary_subject": "Computer Vision and Pattern Recognition (cs.CV)",
      "subject_categories": [
        "cs.CV",
        "eess.IV"
      ],
      "announcement_date": "2026-03-26"
    },
    {
      "paper_id": "2603.24577",
      "abs_url": "https://arxiv.org/abs/2603.24577",
      "source_category": "cs.CV",
      "title": "EndoVGGT: GNN-Enhanced Depth Estimation for Surgical 3D Reconstruction",
      "authors": [
        "Falong Fan",
        "Yi Xie",
        "Arnis Lektauers",
        "Bo Liu",
        "Jerzy Rozenblit"
      ],
      "primary_subject": "Computer Vision and Pattern Recognition (cs.CV)",
      "subject_categories": [
        "cs.AI",
        "cs.CV"
      ],
      "announcement_date": "2026-03-26"
    },
    {
      "paper_id": "2603.24575",
      "abs_url": "https://arxiv.org/abs/2603.24575",
      "source_category": "cs.CV",
      "title": "VFIG: Vectorizing Complex Figures in SVG with Vision-Language Models",
      "authors": [
        "Qijia He",
        "Xunmei Liu",
        "Hammaad Memon",
        "Ziang Li",
        "Zixian Ma",
        "Jaemin Cho",
        "Jason Ren",
        "Daniel S Weld",
        "Ranjay Krishna"
      ],
      "primary_subject": "Computer Vision and Pattern Recognition (cs.CV)",
      "subject_categories": [
        "cs.AI",
        "cs.CV"
      ],
      "announcement_date": "2026-03-26"
    },
    {
      "paper_id": "2603.24571",
      "abs_url": "https://arxiv.org/abs/2603.24571",
      "source_category": "cs.CV",
      "title": "Towards Training-Free Scene Text Editing",
      "authors": [
        "Yubo Li",
        "Xugong Qin",
        "Peng Zhang",
        "Hailun Lin",
        "Gangyan Zeng",
        "Kexin Zhang"
      ],
      "primary_subject": "Computer Vision and Pattern Recognition (cs.CV)",
      "subject_categories": [
        "cs.CV"
      ],
      "announcement_date": "2026-03-26"
    },
    {
      "paper_id": "2603.24570",
      "abs_url": "https://arxiv.org/abs/2603.24570",
      "source_category": "cs.CV",
      "title": "Anti-I2V: Safeguarding your photos from malicious image-to-video generation",
      "authors": [
        "Duc Vu",
        "Anh Nguyen",
        "Chi Tran",
        "Anh Tran"
      ],
      "primary_subject": "Computer Vision and Pattern Recognition (cs.CV)",
      "subject_categories": [
        "cs.AI",
        "cs.CV"
      ],
      "announcement_date": "2026-03-26"
    },
    {
      "paper_id": "2603.24569",
      "abs_url": "https://arxiv.org/abs/2603.24569",
      "source_category": "cs.CV",
      "title": "POLY-SIM: Polyglot Speaker Identification with Missing Modality Grand Challenge 2026 Evaluation Plan",
      "authors": [
        "Marta Moscati",
        "Muhammad Saad Saeed",
        "Marina Zanoni",
        "Mubashir Noman",
        "Rohan Kumar Das",
        "Monorama Swain",
        "Yufang Hou",
        "Elisabeth Andre",
        "Khalid Mahmood Malik",
        "Markus Schedl",
        "Shah Nawaz"
      ],
      "primary_subject": "Computer Vision and Pattern Recognition (cs.CV)",
      "subject_categories": [
        "cs.CV"
      ],
      "announcement_date": "2026-03-26"
    },
    {
      "paper_id": "2603.24558",
      "abs_url": "https://arxiv.org/abs/2603.24558",
      "source_category": "cs.CV",
      "title": "LensWalk: Agentic Video Understanding by Planning How You See in Videos",
      "authors": [
        "Keliang Li",
        "Yansong Li",
        "Hongze Shen",
        "Mengdi Liu",
        "Hong Chang",
        "Shiguang Shan"
      ],
      "primary_subject": "Computer Vision and Pattern Recognition (cs.CV)",
      "subject_categories": [
        "cs.AI",
        "cs.CV"
      ],
      "announcement_date": "2026-03-26"
    },
    {
      "paper_id": "2603.24552",
      "abs_url": "https://arxiv.org/abs/2603.24552",
      "source_category": "cs.CV",
      "title": "The role of spatial context and multitask learning in the detection of organic and conventional farming systems based on Sentinel-2 time series",
      "authors": [
        "Jan Hemmerling",
        "Marcel Schwieder",
        "Philippe Rufin",
        "Leon-Friedrich Thomas",
        "Mirela Tulbure",
        "Patrick Hostert",
        "Stefan Erasmi"
      ],
      "primary_subject": "Computer Vision and Pattern Recognition (cs.CV)",
      "subject_categories": [
        "cs.CV"
      ],
      "announcement_date": "2026-03-26"
    },
    {
      "paper_id": "2603.24541",
      "abs_url": "https://arxiv.org/abs/2603.24541",
      "source_category": "cs.CV",
      "title": "SEGAR: Selective Enhancement for Generative Augmented Reality",
      "authors": [
        "Fanjun Bu",
        "Chenyang Yuan",
        "Hiroshi Yasuda"
      ],
      "primary_subject": "Computer Vision and Pattern Recognition (cs.CV)",
      "subject_categories": [
        "cs.AI",
        "cs.CV"
      ],
      "announcement_date": "2026-03-26"
    },
    {
      "paper_id": "2603.24539",
      "abs_url": "https://arxiv.org/abs/2603.24539",
      "source_category": "cs.CV",
      "title": "CliPPER: Contextual Video-Language Pretraining on Long-form Intraoperative Surgical Procedures for Event Recognition",
      "authors": [
        "Florian Stilz",
        "Vinkle Srivastav",
        "Nassir Navab",
        "Nicolas Padoy"
      ],
      "primary_subject": "Computer Vision and Pattern Recognition (cs.CV)",
      "subject_categories": [
        "cs.AI",
        "cs.CV"
      ],
      "announcement_date": "2026-03-26"
    },
    {
      "paper_id": "2603.24528",
      "abs_url": "https://arxiv.org/abs/2603.24528",
      "source_category": "cs.CV",
      "title": "Cross-Modal Prototype Alignment and Mixing for Training-Free Few-Shot Classification",
      "authors": [
        "Dipam Goswami",
        "Simone Magistri",
        "Gido M. van de Ven",
        "Bartłomiej Twardowski",
        "Andrew D. Bagdanov",
        "Tinne Tuytelaars",
        "Joost van de Weijer"
      ],
      "primary_subject": "Computer Vision and Pattern Recognition (cs.CV)",
      "subject_categories": [
        "cs.CV"
      ],
      "announcement_date": "2026-03-26"
    },
    {
      "paper_id": "2603.24506",
      "abs_url": "https://arxiv.org/abs/2603.24506",
      "source_category": "cs.CV",
      "title": "Toward Physically Consistent Driving Video World Models under Challenging Trajectories",
      "authors": [
        "Jiawei Zhou",
        "Zhenxin Zhu",
        "Lingyi Du",
        "Linye Lyu",
        "Lijun Zhou",
        "Zhanqian Wu",
        "Hongcheng Luo",
        "Zhuotao Tian",
        "Bing Wang",
        "Guang Chen",
        "Hangjun Ye",
        "Haiyang Sun",
        "Yu Li"
      ],
      "primary_subject": "Computer Vision and Pattern Recognition (cs.CV)",
      "subject_categories": [
        "cs.CV"
      ],
      "announcement_date": "2026-03-26"
    },
    {
      "paper_id": "2603.24484",
      "abs_url": "https://arxiv.org/abs/2603.24484",
      "source_category": "cs.CV",
      "title": "Video-Only ToM: Enhancing Theory of Mind in Multimodal Large Language Models",
      "authors": [
        "Siqi Liu",
        "Xinyang Li",
        "Bochao Zou",
        "Junbao Zhuo",
        "Huimin Ma",
        "Jiansheng Chen"
      ],
      "primary_subject": "Computer Vision and Pattern Recognition (cs.CV)",
      "subject_categories": [
        "cs.CV"
      ],
      "announcement_date": "2026-03-26"
    },
    {
      "paper_id": "2603.24480",
      "abs_url": "https://arxiv.org/abs/2603.24480",
      "source_category": "cs.CV",
      "title": "Positive-First Most Ambiguous: A Simple Active Learning Criterion for Interactive Retrieval of Rare Categories",
      "authors": [
        "Kawtar Zaher",
        "Olivier Buisson",
        "Alexis Joly"
      ],
      "primary_subject": "Computer Vision and Pattern Recognition (cs.CV)",
      "subject_categories": [
        "cs.CV",
        "cs.HC",
        "cs.IR"
      ],
      "announcement_date": "2026-03-26"
    },
    {
      "paper_id": "2603.24470",
      "abs_url": "https://arxiv.org/abs/2603.24470",
      "source_category": "cs.CV",
      "title": "Counting Without Numbers \\& Finding Without Words",
      "authors": [
        "Badri Narayana Patro"
      ],
      "primary_subject": "Computer Vision and Pattern Recognition (cs.CV)",
      "subject_categories": [
        "cs.AI",
        "cs.CL",
        "cs.CV",
        "cs.SI"
      ],
      "announcement_date": "2026-03-26"
    },
    {
      "paper_id": "2603.24458",
      "abs_url": "https://arxiv.org/abs/2603.24458",
      "source_category": "cs.CV",
      "title": "OmniWeaving: Towards Unified Video Generation with Free-form Composition and Reasoning",
      "authors": [
        "Kaihang Pan",
        "Qi Tian",
        "Jianwei Zhang",
        "Weijie Kong",
        "Jiangfeng Xiong",
        "Yanxin Long",
        "Shixue Zhang",
        "Haiyi Qiu",
        "Tan Wang",
        "Zheqi Lv",
        "Yue Wu",
        "Liefeng Bo",
        "Siliang Tang",
        "Zhao Zhong"
      ],
      "primary_subject": "Computer Vision and Pattern Recognition (cs.CV)",
      "subject_categories": [
        "cs.CV"
      ],
      "announcement_date": "2026-03-26"
    },
    {
      "paper_id": "2603.24454",
      "abs_url": "https://arxiv.org/abs/2603.24454",
      "source_category": "cs.CV",
      "title": "Unleashing Vision-Language Semantics for Deepfake Video Detection",
      "authors": [
        "Jiawen Zhu",
        "Yunqi Miao",
        "Xueyi Zhang",
        "Jiankang Deng",
        "Guansong Pang"
      ],
      "primary_subject": "Computer Vision and Pattern Recognition (cs.CV)",
      "subject_categories": [
        "cs.CV"
      ],
      "announcement_date": "2026-03-26"
    },
    {
      "paper_id": "2603.24434",
      "abs_url": "https://arxiv.org/abs/2603.24434",
      "source_category": "cs.CV",
      "title": "The Gait Signature of Frailty: Transfer Learning based Deep Gait Models for Scalable Frailty Assessment",
      "authors": [
        "Laura McDaniel",
        "Basudha Pal",
        "Crystal Szczesny",
        "Yuxiang Guo",
        "Ryan Roemmich",
        "Peter Abadir",
        "Rama Chellappa"
      ],
      "primary_subject": "Computer Vision and Pattern Recognition (cs.CV)",
      "subject_categories": [
        "cs.CV"
      ],
      "announcement_date": "2026-03-26"
    },
    {
      "paper_id": "2603.24407",
      "abs_url": "https://arxiv.org/abs/2603.24407",
      "source_category": "cs.CV",
      "title": "Teacher-Student Diffusion Model for Text-Driven 3D Hand Motion Generation",
      "authors": [
        "Ching-Lam Cheng",
        "Bin Zhu",
        "Shengfeng He"
      ],
      "primary_subject": "Computer Vision and Pattern Recognition (cs.CV)",
      "subject_categories": [
        "cs.CV"
      ],
      "announcement_date": "2026-03-26"
    },
    {
      "paper_id": "2603.24388",
      "abs_url": "https://arxiv.org/abs/2603.24388",
      "source_category": "cs.CV",
      "title": "Causal Transfer in Medical Image Analysis",
      "authors": [
        "Mohammed M. Abdelsamea",
        "Daniel Tweneboah Anyimadu",
        "Tasneem Selim",
        "Saif Alzubi",
        "Lei Zhang",
        "Ahmed Karam Eldaly",
        "Xujiong Ye"
      ],
      "primary_subject": "Computer Vision and Pattern Recognition (cs.CV)",
      "subject_categories": [
        "cs.CV"
      ],
      "announcement_date": "2026-03-26"
    },
    {
      "paper_id": "2603.24383",
      "abs_url": "https://arxiv.org/abs/2603.24383",
      "source_category": "cs.CV",
      "title": "ViHOI: Human-Object Interaction Synthesis with Visual Priors",
      "authors": [
        "Songjin Cai",
        "Linjie Zhong",
        "Ling Guo",
        "Changxing Ding"
      ],
      "primary_subject": "Computer Vision and Pattern Recognition (cs.CV)",
      "subject_categories": [
        "cs.CV"
      ],
      "announcement_date": "2026-03-26"
    },
    {
      "paper_id": "2603.24376",
      "abs_url": "https://arxiv.org/abs/2603.24376",
      "source_category": "cs.CV",
      "title": "GeoRouter: Dynamic Paradigm Routing for Worldwide Image Geolocalization",
      "authors": [
        "Pengyue Jia",
        "Derong Xu",
        "Yingyi Zhang",
        "Xiaopeng Li",
        "Wenlin Zhang",
        "Yi Wen",
        "Yuanshao Zhu",
        "Xiangyu Zhao"
      ],
      "primary_subject": "Computer Vision and Pattern Recognition (cs.CV)",
      "subject_categories": [
        "cs.CV"
      ],
      "announcement_date": "2026-03-26"
    },
    {
      "paper_id": "2603.24373",
      "abs_url": "https://arxiv.org/abs/2603.24373",
      "source_category": "cs.CV",
      "title": "PP-OCRv5: A Specialized 5M-Parameter Model Rivaling Billion-Parameter Vision-Language Models on OCR Tasks",
      "authors": [
        "Cheng Cui",
        "Yubo Zhang",
        "Ting Sun",
        "Xueqing Wang",
        "Hongen Liu",
        "Manhui Lin",
        "Yue Zhang",
        "Tingquan Gao",
        "Changda Zhou",
        "Jiaxuan Liu",
        "Zelun Zhang",
        "Jing Zhang",
        "Jun Zhang",
        "Yi Liu"
      ],
      "primary_subject": "Computer Vision and Pattern Recognition (cs.CV)",
      "subject_categories": [
        "cs.CV"
      ],
      "announcement_date": "2026-03-26"
    },
    {
      "paper_id": "2603.24355",
      "abs_url": "https://arxiv.org/abs/2603.24355",
      "source_category": "cs.CV",
      "title": "Language-Guided Structure-Aware Network for Camouflaged Object Detection",
      "authors": [
        "Min Zhang"
      ],
      "primary_subject": "Computer Vision and Pattern Recognition (cs.CV)",
      "subject_categories": [
        "cs.AI",
        "cs.CV"
      ],
      "announcement_date": "2026-03-26"
    },
    {
      "paper_id": "2603.24327",
      "abs_url": "https://arxiv.org/abs/2603.24327",
      "source_category": "cs.CV",
      "title": "Le MuMo JEPA: Multi-Modal Self-Supervised Representation Learning with Learnable Fusion Tokens",
      "authors": [
        "Ciem Cornelissen",
        "Sam Leroux",
        "Pieter Simoens"
      ],
      "primary_subject": "Computer Vision and Pattern Recognition (cs.CV)",
      "subject_categories": [
        "cs.CV"
      ],
      "announcement_date": "2026-03-26"
    },
    {
      "paper_id": "2603.24326",
      "abs_url": "https://arxiv.org/abs/2603.24326",
      "source_category": "cs.CV",
      "title": "Boosting Document Parsing Efficiency and Performance with Coarse-to-Fine Visual Processing",
      "authors": [
        "Cheng Cui",
        "Ting Sun",
        "Suyin Liang",
        "Tingquan Gao",
        "Zelun Zhang",
        "Jiaxuan Liu",
        "Xueqing Wang",
        "Changda Zhou",
        "Hongen Liu",
        "Manhui Lin",
        "Yue Zhang",
        "Yubo Zhang",
        "Jing Zhang",
        "Jun Zhang",
        "Xing Wei",
        "Yi Liu",
        "Dianhai Yu",
        "Yanjun Ma"
      ],
      "primary_subject": "Computer Vision and Pattern Recognition (cs.CV)",
      "subject_categories": [
        "cs.AI",
        "cs.CV",
        "cs.IR"
      ],
      "announcement_date": "2026-03-26"
    },
    {
      "paper_id": "2603.24322",
      "abs_url": "https://arxiv.org/abs/2603.24322",
      "source_category": "cs.CV",
      "title": "Heuristic Self-Paced Learning for Domain Adaptive Semantic Segmentation under Adverse Conditions",
      "authors": [
        "Shiqin Wang",
        "Haoyang Chen",
        "Huaizhou Huang",
        "Yinkan He",
        "Dongfang Sun",
        "Xiaoqing Chen",
        "Xingyu Liu",
        "Zheng Wang",
        "Kaiyan Zhao"
      ],
      "primary_subject": "Computer Vision and Pattern Recognition (cs.CV)",
      "subject_categories": [
        "cs.CV"
      ],
      "announcement_date": "2026-03-26"
    },
    {
      "paper_id": "2603.24312",
      "abs_url": "https://arxiv.org/abs/2603.24312",
      "source_category": "cs.CV",
      "title": "Refining time-space traffic diagrams: A neighborhood-adaptive linear regression method",
      "authors": [
        "Zhihong Yao",
        "Yi Yu",
        "Yunxia Wu",
        "Hao Li",
        "Yangsheng Jiang",
        "Zhengbing He"
      ],
      "primary_subject": "Computer Vision and Pattern Recognition (cs.CV)",
      "subject_categories": [
        "cs.CV"
      ],
      "announcement_date": "2026-03-26"
    },
    {
      "paper_id": "2603.24296",
      "abs_url": "https://arxiv.org/abs/2603.24296",
      "source_category": "cs.CV",
      "title": "AMIF: Authorizable Medical Image Fusion Model with Built-in Authentication",
      "authors": [
        "Jie Song",
        "Jun Jia",
        "Wei Sun",
        "Wangqiu Zhou",
        "Tao Tan",
        "Guangtao Zhai"
      ],
      "primary_subject": "Computer Vision and Pattern Recognition (cs.CV)",
      "subject_categories": [
        "cs.CV"
      ],
      "announcement_date": "2026-03-26"
    },
    {
      "paper_id": "2603.24295",
      "abs_url": "https://arxiv.org/abs/2603.24295",
      "source_category": "cs.CV",
      "title": "RS-SSM: Refining Forgotten Specifics in State Space Model for Video Semantic Segmentation",
      "authors": [
        "Kai Zhu",
        "Zhenyu Cui",
        "Zehua Zang",
        "Jiahuan Zhou"
      ],
      "primary_subject": "Computer Vision and Pattern Recognition (cs.CV)",
      "subject_categories": [
        "cs.CV"
      ],
      "announcement_date": "2026-03-26"
    },
    {
      "paper_id": "2603.24294",
      "abs_url": "https://arxiv.org/abs/2603.24294",
      "source_category": "cs.CV",
      "title": "VERIA: Verification-Centric Multimodal Instance Augmentation for Long-Tailed 3D Object Detection",
      "authors": [
        "Jumin Lee",
        "Siyeong Lee",
        "Namil Kim",
        "Sung-Eui Yoon"
      ],
      "primary_subject": "Computer Vision and Pattern Recognition (cs.CV)",
      "subject_categories": [
        "cs.CV"
      ],
      "announcement_date": "2026-03-26"
    },
    {
      "paper_id": "2603.24278",
      "abs_url": "https://arxiv.org/abs/2603.24278",
      "source_category": "cs.CV",
      "title": "TopoMesh: High-Fidelity Mesh Autoencoding via Topological Unification",
      "authors": [
        "Guan Luo",
        "Xiu Li",
        "Rui Chen",
        "Xuanyu Yi",
        "Jing Lin",
        "Chia-Hao Chen",
        "Jiahang Liu",
        "Song-Hai Zhang",
        "Jianfeng Zhang"
      ],
      "primary_subject": "Computer Vision and Pattern Recognition (cs.CV)",
      "subject_categories": [
        "cs.CV"
      ],
      "announcement_date": "2026-03-26"
    },
    {
      "paper_id": "2603.24270",
      "abs_url": "https://arxiv.org/abs/2603.24270",
      "source_category": "cs.CV",
      "title": "ScrollScape: Unlocking 32K Image Generation With Video Diffusion Priors",
      "authors": [
        "Haodong Yu",
        "Yabo Zhang",
        "Donglin Di",
        "Ruyi Zhang",
        "Wangmeng Zuo"
      ],
      "primary_subject": "Computer Vision and Pattern Recognition (cs.CV)",
      "subject_categories": [
        "cs.CV"
      ],
      "announcement_date": "2026-03-26"
    },
    {
      "paper_id": "2603.24260",
      "abs_url": "https://arxiv.org/abs/2603.24260",
      "source_category": "cs.CV",
      "title": "Accelerating Diffusion-based Video Editing via Heterogeneous Caching: Beyond Full Computing at Sampled Denoising Timestep",
      "authors": [
        "Tianyi Liu",
        "Ye Lu",
        "Linfeng Zhang",
        "Chen Cai",
        "Jianjun Gao",
        "Yi Wang",
        "Kim-Hui Yap",
        "Lap-Pui Chau"
      ],
      "primary_subject": "Computer Vision and Pattern Recognition (cs.CV)",
      "subject_categories": [
        "cs.AI",
        "cs.CV"
      ],
      "announcement_date": "2026-03-26"
    },
    {
      "paper_id": "2603.24257",
      "abs_url": "https://arxiv.org/abs/2603.24257",
      "source_category": "cs.CV",
      "title": "Memory-Augmented Vision-Language Agents for Persistent and Semantically Consistent Object Captioning",
      "authors": [
        "Tommaso Galliena",
        "Stefano Rosa",
        "Tommaso Apicella",
        "Pietro Morerio",
        "Alessio Del Bue",
        "Lorenzo Natale"
      ],
      "primary_subject": "Computer Vision and Pattern Recognition (cs.CV)",
      "subject_categories": [
        "cs.CV"
      ],
      "announcement_date": "2026-03-26"
    },
    {
      "paper_id": "2603.24245",
      "abs_url": "https://arxiv.org/abs/2603.24245",
      "source_category": "cs.CV",
      "title": "B-MoE: A Body-Part-Aware Mixture-of-Experts \"All Parts Matter\" Approach to Micro-Action Recognition",
      "authors": [
        "Nishit Poddar",
        "Aglind Reka",
        "Diana-Laura Borza",
        "Snehashis Majhi",
        "Michal Balazia",
        "Abhijit Das",
        "Francois Bremond"
      ],
      "primary_subject": "Computer Vision and Pattern Recognition (cs.CV)",
      "subject_categories": [
        "cs.CV"
      ],
      "announcement_date": "2026-03-26"
    },
    {
      "paper_id": "2603.24240",
      "abs_url": "https://arxiv.org/abs/2603.24240",
      "source_category": "cs.CV",
      "title": "InstanceRSR: Real-World Super-Resolution via Instance-Aware Representation Alignment",
      "authors": [
        "Zixin Guo",
        "Kai Zhao",
        "Luyan Zhang"
      ],
      "primary_subject": "Computer Vision and Pattern Recognition (cs.CV)",
      "subject_categories": [
        "cs.CV"
      ],
      "announcement_date": "2026-03-26"
    },
    {
      "paper_id": "2603.24224",
      "abs_url": "https://arxiv.org/abs/2603.24224",
      "source_category": "cs.CV",
      "title": "RVLM: Recursive Vision-Language Models with Adaptive Depth",
      "authors": [
        "Nicanor Mayumu",
        "Zeenath Khan",
        "Melodena Stephens",
        "Patrick Mukala",
        "Farhad Oroumchian"
      ],
      "primary_subject": "Computer Vision and Pattern Recognition (cs.CV)",
      "subject_categories": [
        "cs.CV"
      ],
      "announcement_date": "2026-03-26"
    },
    {
      "paper_id": "2603.24209",
      "abs_url": "https://arxiv.org/abs/2603.24209",
      "source_category": "cs.CV",
      "title": "HEART-PFL: Stable Personalized Federated Learning under Heterogeneity with Hierarchical Directional Alignment and Adversarial Knowledge Transfer",
      "authors": [
        "Minjun Kim",
        "Minje Kim"
      ],
      "primary_subject": "Computer Vision and Pattern Recognition (cs.CV)",
      "subject_categories": [
        "cs.CV",
        "cs.LG"
      ],
      "announcement_date": "2026-03-26"
    },
    {
      "paper_id": "2603.24208",
      "abs_url": "https://arxiv.org/abs/2603.24208",
      "source_category": "cs.CV",
      "title": "Powerful Teachers Matter: Text-Guided Multi-view Knowledge Distillation with Visual Prior Enhancement",
      "authors": [
        "Xin Zhang",
        "Jianyang Xu",
        "Hao Peng",
        "Dongjing Wang",
        "Jingyuan Zheng",
        "Yu Li",
        "Yuyu Yin",
        "Hongbo Wang"
      ],
      "primary_subject": "Computer Vision and Pattern Recognition (cs.CV)",
      "subject_categories": [
        "cs.AI",
        "cs.CV"
      ],
      "announcement_date": "2026-03-26"
    },
    {
      "paper_id": "2603.24198",
      "abs_url": "https://arxiv.org/abs/2603.24198",
      "source_category": "cs.CV",
      "title": "RefReward-SR: LR-Conditioned Reward Modeling for Preference-Aligned Super-Resolution",
      "authors": [
        "Yushuai Song",
        "Weize Quan",
        "Weining Wang",
        "Jiahui Sun",
        "Jing Liu",
        "Meng Li",
        "Pengbin Yu",
        "Zhentao Chen",
        "Wei Shen",
        "Lunxi Yuan",
        "Dong-ming Yan"
      ],
      "primary_subject": "Computer Vision and Pattern Recognition (cs.CV)",
      "subject_categories": [
        "cs.CV"
      ],
      "announcement_date": "2026-03-26"
    },
    {
      "paper_id": "2603.24181",
      "abs_url": "https://arxiv.org/abs/2603.24181",
      "source_category": "cs.CV",
      "title": "Unlocking Few-Shot Capabilities in LVLMs via Prompt Conditioning and Head Selection",
      "authors": [
        "Adhemar de Senneville",
        "Xavier Bou",
        "Jérémy Anger",
        "Rafael Grompone",
        "Gabriele Facciolo"
      ],
      "primary_subject": "Computer Vision and Pattern Recognition (cs.CV)",
      "subject_categories": [
        "cs.CV"
      ],
      "announcement_date": "2026-03-26"
    },
    {
      "paper_id": "2603.24166",
      "abs_url": "https://arxiv.org/abs/2603.24166",
      "source_category": "cs.CV",
      "title": "Heuristic-inspired Reasoning Priors Facilitate Data-Efficient Referring Object Detection",
      "authors": [
        "Xu Zhang",
        "Zhe Chen",
        "Jing Zhang",
        "Dacheng Tao"
      ],
      "primary_subject": "Computer Vision and Pattern Recognition (cs.CV)",
      "subject_categories": [
        "cs.CV"
      ],
      "announcement_date": "2026-03-26"
    },
    {
      "paper_id": "2603.24157",
      "abs_url": "https://arxiv.org/abs/2603.24157",
      "source_category": "cs.CV",
      "title": "CarePilot: A Multi-Agent Framework for Long-Horizon Computer Task Automation in Healthcare",
      "authors": [
        "Akash Ghosh",
        "Tajamul Ashraf",
        "Rishu Kumar Singh",
        "Numan Saeed",
        "Sriparna Saha",
        "Xiuying Chen",
        "Salman Khan"
      ],
      "primary_subject": "Computer Vision and Pattern Recognition (cs.CV)",
      "subject_categories": [
        "cs.CV"
      ],
      "announcement_date": "2026-03-26"
    },
    {
      "paper_id": "2603.24156",
      "abs_url": "https://arxiv.org/abs/2603.24156",
      "source_category": "cs.CV",
      "title": "A convergent Plug-and-Play Majorization-Minimization algorithm for Poisson inverse problems",
      "authors": [
        "Thibaut Modrzyk",
        "Ane Etxebeste",
        "Élie Bretin",
        "Voichita Maxim"
      ],
      "primary_subject": "Computer Vision and Pattern Recognition (cs.CV)",
      "subject_categories": [
        "cs.CV"
      ],
      "announcement_date": "2026-03-26"
    },
    {
      "paper_id": "2603.24146",
      "abs_url": "https://arxiv.org/abs/2603.24146",
      "source_category": "cs.CV",
      "title": "LightSplat: Fast and Memory-Efficient Open-Vocabulary 3D Scene Understanding in Five Seconds",
      "authors": [
        "Jaehun Bang",
        "Jinhyeok Kim",
        "Minji Kim",
        "Seungheon Jeong",
        "Kyungdon Joo"
      ],
      "primary_subject": "Computer Vision and Pattern Recognition (cs.CV)",
      "subject_categories": [
        "cs.CV"
      ],
      "announcement_date": "2026-03-26"
    },
    {
      "paper_id": "2603.24139",
      "abs_url": "https://arxiv.org/abs/2603.24139",
      "source_category": "cs.CV",
      "title": "Tutor-Student Reinforcement Learning: A Dynamic Curriculum for Robust Deepfake Detection",
      "authors": [
        "Zhanhe Lei",
        "Zhongyuan Wang",
        "Jikang Cheng",
        "Baojin Huang",
        "Yuhong Yang",
        "Zhen Han",
        "Chao Liang",
        "Dengpan Ye"
      ],
      "primary_subject": "Computer Vision and Pattern Recognition (cs.CV)",
      "subject_categories": [
        "cs.CV",
        "cs.LG"
      ],
      "announcement_date": "2026-03-26"
    },
    {
      "paper_id": "2603.24134",
      "abs_url": "https://arxiv.org/abs/2603.24134",
      "source_category": "cs.CV",
      "title": "Spectral Scalpel: Amplifying Adjacent Action Discrepancy via Frequency-Selective Filtering for Skeleton-Based Action Segmentation",
      "authors": [
        "Haoyu Ji",
        "Bowen Chen",
        "Zhihao Yang",
        "Wenze Huang",
        "Yu Gao",
        "Xueting Liu",
        "Weihong Ren",
        "Zhiyong Wang",
        "Honghai Liu"
      ],
      "primary_subject": "Computer Vision and Pattern Recognition (cs.CV)",
      "subject_categories": [
        "cs.CV"
      ],
      "announcement_date": "2026-03-26"
    },
    {
      "paper_id": "2603.24117",
      "abs_url": "https://arxiv.org/abs/2603.24117",
      "source_category": "cs.CV",
      "title": "Combi-CAM: A Novel Multi-Layer Approach for Explainable Image Geolocalization",
      "authors": [
        "David Faget",
        "José Luis Lisani",
        "Miguel Colom"
      ],
      "primary_subject": "Computer Vision and Pattern Recognition (cs.CV)",
      "subject_categories": [
        "cs.CV"
      ],
      "announcement_date": "2026-03-26"
    },
    {
      "paper_id": "2603.24115",
      "abs_url": "https://arxiv.org/abs/2603.24115",
      "source_category": "cs.CV",
      "title": "Retinal Layer Segmentation in OCT Images With 2.5D Cross-slice Feature Fusion Module for Glaucoma Assessment",
      "authors": [
        "Hyunwoo Kim",
        "Heesuk Kim",
        "Wungrak Choi",
        "Jae-Sang Hyun"
      ],
      "primary_subject": "Computer Vision and Pattern Recognition (cs.CV)",
      "subject_categories": [
        "cs.CV"
      ],
      "announcement_date": "2026-03-26"
    },
    {
      "paper_id": "2603.24106",
      "abs_url": "https://arxiv.org/abs/2603.24106",
      "source_category": "cs.CV",
      "title": "Granular Ball Guided Stable Latent Domain Discovery for Domain-General Crowd Counting",
      "authors": [
        "Fan Chen",
        "Shuyin Xia",
        "Yi Wang",
        "Xinbo Gao"
      ],
      "primary_subject": "Computer Vision and Pattern Recognition (cs.CV)",
      "subject_categories": [
        "cs.CV"
      ],
      "announcement_date": "2026-03-26"
    },
    {
      "paper_id": "2603.24097",
      "abs_url": "https://arxiv.org/abs/2603.24097",
      "source_category": "cs.CV",
      "title": "LaDy: Lagrangian-Dynamic Informed Network for Skeleton-based Action Segmentation via Spatial-Temporal Modulation",
      "authors": [
        "Haoyu Ji",
        "Xueting Liu",
        "Yu Gao",
        "Wenze Huang",
        "Zhihao Yang",
        "Weihong Ren",
        "Zhiyong Wang",
        "Honghai Liu"
      ],
      "primary_subject": "Computer Vision and Pattern Recognition (cs.CV)",
      "subject_categories": [
        "cs.CV"
      ],
      "announcement_date": "2026-03-26"
    },
    {
      "paper_id": "2603.24086",
      "abs_url": "https://arxiv.org/abs/2603.24086",
      "source_category": "cs.CV",
      "title": "LGTM: Training-Free Light-Guided Text-to-Image Diffusion Model via Initial Noise Manipulation",
      "authors": [
        "Ryugo Morita",
        "Stanislav Frolov",
        "Brian Bernhard Moser",
        "Ko Watanabe",
        "Riku Takahashi",
        "Andreas Dengel"
      ],
      "primary_subject": "Computer Vision and Pattern Recognition (cs.CV)",
      "subject_categories": [
        "cs.CV",
        "cs.GR"
      ],
      "announcement_date": "2026-03-26"
    },
    {
      "paper_id": "2603.24079",
      "abs_url": "https://arxiv.org/abs/2603.24079",
      "source_category": "cs.CV",
      "title": "When Understanding Becomes a Risk: Authenticity and Safety Risks in the Emerging Image Generation Paradigm",
      "authors": [
        "Ye Leng",
        "Junjie Chu",
        "Mingjie Li",
        "Chenhao Lin",
        "Chao Shen",
        "Michael Backes",
        "Yun Shen",
        "Yang Zhang"
      ],
      "primary_subject": "Computer Vision and Pattern Recognition (cs.CV)",
      "subject_categories": [
        "cs.AI",
        "cs.CR",
        "cs.CV"
      ],
      "announcement_date": "2026-03-26"
    },
    {
      "paper_id": "2603.24078",
      "abs_url": "https://arxiv.org/abs/2603.24078",
      "source_category": "cs.CV",
      "title": "PosterIQ: A Design Perspective Benchmark for Poster Understanding and Generation",
      "authors": [
        "Yuheng Feng",
        "Wen Zhang",
        "Haodong Duan",
        "Xingxing Zou"
      ],
      "primary_subject": "Computer Vision and Pattern Recognition (cs.CV)",
      "subject_categories": [
        "cs.CV"
      ],
      "announcement_date": "2026-03-26"
    },
    {
      "paper_id": "2603.24059",
      "abs_url": "https://arxiv.org/abs/2603.24059",
      "source_category": "cs.CV",
      "title": "AD-Reasoning: Multimodal Guideline-Guided Reasoning for Alzheimer's Disease Diagnosis",
      "authors": [
        "Qiuhui Chen",
        "Yushan Deng",
        "Xuancheng Yao",
        "Yi Hong"
      ],
      "primary_subject": "Computer Vision and Pattern Recognition (cs.CV)",
      "subject_categories": [
        "cs.CV"
      ],
      "announcement_date": "2026-03-26"
    },
    {
      "paper_id": "2603.24058",
      "abs_url": "https://arxiv.org/abs/2603.24058",
      "source_category": "cs.CV",
      "title": "Mitigating Object Hallucinations in LVLMs via Attention Imbalance Rectification",
      "authors": [
        "Han Sun",
        "Qin Li",
        "Peixin Wang",
        "Min Zhang"
      ],
      "primary_subject": "Computer Vision and Pattern Recognition (cs.CV)",
      "subject_categories": [
        "cs.AI",
        "cs.CV"
      ],
      "announcement_date": "2026-03-26"
    },
    {
      "paper_id": "2603.24057",
      "abs_url": "https://arxiv.org/abs/2603.24057",
      "source_category": "cs.CV",
      "title": "Beyond Semantic Priors: Mitigating Optimization Collapse for Generalizable Visual Forensics",
      "authors": [
        "Jipeng Liu",
        "Haichao Shi",
        "Siyu Xing",
        "Rong Yin",
        "Xiao-Yu Zhang"
      ],
      "primary_subject": "Computer Vision and Pattern Recognition (cs.CV)",
      "subject_categories": [
        "cs.CV"
      ],
      "announcement_date": "2026-03-26"
    },
    {
      "paper_id": "2603.24045",
      "abs_url": "https://arxiv.org/abs/2603.24045",
      "source_category": "cs.CV",
      "title": "LGEST: Dynamic Spatial-Spectral Expert Routing for Hyperspectral Image Classification",
      "authors": [
        "Jiawen Wen",
        "Suixuan Qiu",
        "Zihang Luo",
        "Xiaofei Yang",
        "Haotian Shi"
      ],
      "primary_subject": "Computer Vision and Pattern Recognition (cs.CV)",
      "subject_categories": [
        "cs.CV"
      ],
      "announcement_date": "2026-03-26"
    },
    {
      "paper_id": "2603.24043",
      "abs_url": "https://arxiv.org/abs/2603.24043",
      "source_category": "cs.CV",
      "title": "HAM: A Training-Free Style Transfer Approach via Heterogeneous Attention Modulation for Diffusion Models",
      "authors": [
        "Yeqi He",
        "Liang Li",
        "Zhiwen Yang",
        "Xichun Sheng",
        "Zhidong Zhao",
        "Chenggang Yan"
      ],
      "primary_subject": "Computer Vision and Pattern Recognition (cs.CV)",
      "subject_categories": [
        "cs.CV"
      ],
      "announcement_date": "2026-03-26"
    },
    {
      "paper_id": "2603.24039",
      "abs_url": "https://arxiv.org/abs/2603.24039",
      "source_category": "cs.CV",
      "title": "SemLayer: Semantic-aware Generative Segmentation and Layer Construction for Abstract Icons",
      "authors": [
        "Haiyang Xu",
        "Ronghuan Wu",
        "Li-Yi Wei",
        "Nanxuan Zhao",
        "Chenxi Liu",
        "Cuong Nguyen",
        "Zhuowen Tu",
        "Zhaowen Wang"
      ],
      "primary_subject": "Computer Vision and Pattern Recognition (cs.CV)",
      "subject_categories": [
        "cs.CV",
        "cs.GR",
        "cs.HC"
      ],
      "announcement_date": "2026-03-26"
    },
    {
      "paper_id": "2603.24037",
      "abs_url": "https://arxiv.org/abs/2603.24037",
      "source_category": "cs.CV",
      "title": "A^3: Towards Advertising Aesthetic Assessment",
      "authors": [
        "Kaiyuan Ji",
        "Yixuan Gao",
        "Lu Sun",
        "Yushuo Zheng",
        "Zijian Chen",
        "Jianbo Zhang",
        "Xiangyang Zhu",
        "Yuan Tian",
        "Zicheng Zhang",
        "Guangtao Zhai"
      ],
      "primary_subject": "Computer Vision and Pattern Recognition (cs.CV)",
      "subject_categories": [
        "cs.CV"
      ],
      "announcement_date": "2026-03-26"
    },
    {
      "paper_id": "2603.24036",
      "abs_url": "https://arxiv.org/abs/2603.24036",
      "source_category": "cs.CV",
      "title": "SpectralSplats: Robust Differentiable Tracking via Spectral Moment Supervision",
      "authors": [
        "Avigail Cohen Rimon",
        "Amir Mann",
        "Mirela Ben Chen",
        "Or Litany"
      ],
      "primary_subject": "Computer Vision and Pattern Recognition (cs.CV)",
      "subject_categories": [
        "cs.CV"
      ],
      "announcement_date": "2026-03-26"
    },
    {
      "paper_id": "2603.24030",
      "abs_url": "https://arxiv.org/abs/2603.24030",
      "source_category": "cs.CV",
      "title": "Decompose and Transfer: CoT-Prompting Enhanced Alignment for Open-Vocabulary Temporal Action Detection",
      "authors": [
        "Sa Zhu",
        "Wanqian Zhang",
        "Lin Wang",
        "Xiaohua Chen",
        "Chenxu Cui",
        "Jinchao Zhang",
        "Bo Li"
      ],
      "primary_subject": "Computer Vision and Pattern Recognition (cs.CV)",
      "subject_categories": [
        "cs.CV",
        "cs.MM"
      ],
      "announcement_date": "2026-03-26"
    },
    {
      "paper_id": "2603.24016",
      "abs_url": "https://arxiv.org/abs/2603.24016",
      "source_category": "cs.CV",
      "title": "COVTrack++: Learning Open-Vocabulary Multi-Object Tracking from Continuous Videos via a Synergistic Paradigm",
      "authors": [
        "Zekun Qian",
        "Wei Feng",
        "Ruize Han",
        "Junhui Hou"
      ],
      "primary_subject": "Computer Vision and Pattern Recognition (cs.CV)",
      "subject_categories": [
        "cs.CV",
        "cs.LG"
      ],
      "announcement_date": "2026-03-26"
    },
    {
      "paper_id": "2603.24006",
      "abs_url": "https://arxiv.org/abs/2603.24006",
      "source_category": "cs.CV",
      "title": "UW-VOS: A Large-Scale Dataset for Underwater Video Object Segmentation",
      "authors": [
        "Hongshen Zhao",
        "Jingkang Tai",
        "Yuhang Wu",
        "Wenkang Zhang",
        "Xi Lan",
        "Shangyan Wang",
        "Tianyu Zhang",
        "Wankou Yang"
      ],
      "primary_subject": "Computer Vision and Pattern Recognition (cs.CV)",
      "subject_categories": [
        "cs.CV"
      ],
      "announcement_date": "2026-03-26"
    },
    {
      "paper_id": "2603.24005",
      "abs_url": "https://arxiv.org/abs/2603.24005",
      "source_category": "cs.CV",
      "title": "DB SwinT: A Dual-Branch Swin Transformer Network for Road Extraction in Optical Remote Sensing Imagery",
      "authors": [
        "Zongyang He",
        "Xiangli Yang",
        "Xian Gao",
        "Zhiguo Wang"
      ],
      "primary_subject": "Computer Vision and Pattern Recognition (cs.CV)",
      "subject_categories": [
        "cs.CV"
      ],
      "announcement_date": "2026-03-26"
    },
    {
      "paper_id": "2603.23997",
      "abs_url": "https://arxiv.org/abs/2603.23997",
      "source_category": "cs.CV",
      "title": "HGGT: Robust and Flexible 3D Hand Mesh Reconstruction from Uncalibrated Images",
      "authors": [
        "Yumeng Liu",
        "Xiao-Xiao Long",
        "Marc Habermann",
        "Xuanze Yang",
        "Cheng Lin",
        "Yuan Liu",
        "Yuexin Ma",
        "Wenping Wang",
        "Ligang Liu"
      ],
      "primary_subject": "Computer Vision and Pattern Recognition (cs.CV)",
      "subject_categories": [
        "cs.CV"
      ],
      "announcement_date": "2026-03-26"
    },
    {
      "paper_id": "2603.23988",
      "abs_url": "https://arxiv.org/abs/2603.23988",
      "source_category": "cs.CV",
      "title": "CAKE: Real-time Action Detection via Motion Distillation and Background-aware Contrastive Learning",
      "authors": [
        "Hieu Hoang",
        "Dung Trung Tran",
        "Hong Nguyen",
        "Nam-Phong Nguyen"
      ],
      "primary_subject": "Computer Vision and Pattern Recognition (cs.CV)",
      "subject_categories": [
        "cs.CV"
      ],
      "announcement_date": "2026-03-26"
    },
    {
      "paper_id": "2603.23976",
      "abs_url": "https://arxiv.org/abs/2603.23976",
      "source_category": "cs.CV",
      "title": "SilLang: Improving Gait Recognition with Silhouette Language Encoding",
      "authors": [
        "Ruiyi Zhan",
        "Guozhen Peng",
        "Canyu Chen",
        "Jian Lei",
        "Annan Li"
      ],
      "primary_subject": "Computer Vision and Pattern Recognition (cs.CV)",
      "subject_categories": [
        "cs.CV"
      ],
      "announcement_date": "2026-03-26"
    },
    {
      "paper_id": "2603.23975",
      "abs_url": "https://arxiv.org/abs/2603.23975",
      "source_category": "cs.CV",
      "title": "HyDRA: Hybrid Domain-Aware Robust Architecture for Heterogeneous Collaborative Perception",
      "authors": [
        "Minwoo Song",
        "Minhee Kang",
        "Heejin Ahn"
      ],
      "primary_subject": "Computer Vision and Pattern Recognition (cs.CV)",
      "subject_categories": [
        "cs.CV"
      ],
      "announcement_date": "2026-03-26"
    },
    {
      "paper_id": "2603.23973",
      "abs_url": "https://arxiv.org/abs/2603.23973",
      "source_category": "cs.CV",
      "title": "SLAT-Phys: Fast Material Property Field Prediction from Structured 3D Latents",
      "authors": [
        "Rocktim Jyoti Das",
        "Dinesh Manocha"
      ],
      "primary_subject": "Computer Vision and Pattern Recognition (cs.CV)",
      "subject_categories": [
        "cs.CV",
        "cs.GR",
        "cs.RO"
      ],
      "announcement_date": "2026-03-26"
    },
    {
      "paper_id": "2603.23960",
      "abs_url": "https://arxiv.org/abs/2603.23960",
      "source_category": "cs.CV",
      "title": "Leave No Stone Unturned: Uncovering Holistic Audio-Visual Intrinsic Coherence for Deepfake Detection",
      "authors": [
        "Jielun Peng",
        "Yabin Wang",
        "Yaqi Li",
        "Long Kong",
        "Xiaopeng Hong"
      ],
      "primary_subject": "Computer Vision and Pattern Recognition (cs.CV)",
      "subject_categories": [
        "cs.CV"
      ],
      "announcement_date": "2026-03-26"
    },
    {
      "paper_id": "2603.23957",
      "abs_url": "https://arxiv.org/abs/2603.23957",
      "source_category": "cs.CV",
      "title": "PointRFT: Explicit Reinforcement Fine-tuning for Point Cloud Few-shot Learning",
      "authors": [
        "Yankai Wang",
        "Yiding Sun",
        "Qirui Wang",
        "Pengbo Li",
        "Chaoyi Lu",
        "Dongxu Zhang"
      ],
      "primary_subject": "Computer Vision and Pattern Recognition (cs.CV)",
      "subject_categories": [
        "cs.CV"
      ],
      "announcement_date": "2026-03-26"
    },
    {
      "paper_id": "2603.23956",
      "abs_url": "https://arxiv.org/abs/2603.23956",
      "source_category": "cs.CV",
      "title": "SynMVCrowd: A Large Synthetic Benchmark for Multi-view Crowd Counting and Localization",
      "authors": [
        "Qi Zhang",
        "Daijie Chen",
        "Yunfei Gong",
        "Hui Huang"
      ],
      "primary_subject": "Computer Vision and Pattern Recognition (cs.CV)",
      "subject_categories": [
        "cs.CV"
      ],
      "announcement_date": "2026-03-26"
    },
    {
      "paper_id": "2603.23953",
      "abs_url": "https://arxiv.org/abs/2603.23953",
      "source_category": "cs.CV",
      "title": "VOLMO: Versatile and Open Large Models for Ophthalmology",
      "authors": [
        "Zhenyue Qin",
        "Younjoon Chung",
        "Elijah Lee",
        "Wanyue Feng",
        "Xuguang Ai",
        "Serina Applebaum",
        "Minjie Zou",
        "Yang Liu",
        "Pan Xiao",
        "Mac Singer",
        "Amisha Dave",
        "Aidan Gilson",
        "Tiarnan D. L. Keenan",
        "Emily Y. Chew",
        "Zhiyong Lu",
        "Yih-Chung Tham",
        "Ron Adelman",
        "Luciano V. Del Priore",
        "Qingyu Chen"
      ],
      "primary_subject": "Computer Vision and Pattern Recognition (cs.CV)",
      "subject_categories": [
        "cs.CV",
        "cs.ET"
      ],
      "announcement_date": "2026-03-26"
    },
    {
      "paper_id": "2603.23940",
      "abs_url": "https://arxiv.org/abs/2603.23940",
      "source_category": "cs.CV",
      "title": "High-Fidelity Face Content Recovery via Tamper-Resilient Versatile Watermarking",
      "authors": [
        "Peipeng Yu",
        "Jinfeng Xie",
        "Chengfu Ou",
        "Xiaoyu Zhou",
        "Jianwei Fei",
        "Yunshu Dai",
        "Zhihua Xia",
        "Chip Hong Chang"
      ],
      "primary_subject": "Computer Vision and Pattern Recognition (cs.CV)",
      "subject_categories": [
        "cs.AI",
        "cs.CV"
      ],
      "announcement_date": "2026-03-26"
    },
    {
      "paper_id": "2603.23934",
      "abs_url": "https://arxiv.org/abs/2603.23934",
      "source_category": "cs.CV",
      "title": "Revealing Multi-View Hallucination in Large Vision-Language Models",
      "authors": [
        "Wooje Park",
        "Insu Lee",
        "Soohyun Kim",
        "Jaeyun Jang",
        "Minyoung Noh",
        "Kyuhong Shim",
        "Byonghyo Shim"
      ],
      "primary_subject": "Computer Vision and Pattern Recognition (cs.CV)",
      "subject_categories": [
        "cs.AI",
        "cs.CV"
      ],
      "announcement_date": "2026-03-26"
    },
    {
      "paper_id": "2603.23925",
      "abs_url": "https://arxiv.org/abs/2603.23925",
      "source_category": "cs.CV",
      "title": "DP^2-VL: Private Photo Dataset Protection by Data Poisoning for Vision-Language Models",
      "authors": [
        "Hongyi Miao",
        "Jun Jia",
        "Xincheng Wang",
        "Qianli Ma",
        "Wei Sun",
        "Wangqiu Zhou",
        "Dandan Zhu",
        "Yewen Cao",
        "Zhi Liu",
        "Guangtao Zhai"
      ],
      "primary_subject": "Computer Vision and Pattern Recognition (cs.CV)",
      "subject_categories": [
        "cs.CV"
      ],
      "announcement_date": "2026-03-26"
    },
    {
      "paper_id": "2603.23924",
      "abs_url": "https://arxiv.org/abs/2603.23924",
      "source_category": "cs.CV",
      "title": "DepthArb: Training-Free Depth-Arbitrated Generation for Occlusion-Robust Image Synthesis",
      "authors": [
        "Hongjin Niu",
        "Jiahao Wang",
        "Xirui Hu",
        "Weizhan Zhang",
        "Lan Ma",
        "Yuan Gao"
      ],
      "primary_subject": "Computer Vision and Pattern Recognition (cs.CV)",
      "subject_categories": [
        "cs.CV"
      ],
      "announcement_date": "2026-03-26"
    },
    {
      "paper_id": "2603.23919",
      "abs_url": "https://arxiv.org/abs/2603.23919",
      "source_category": "cs.CV",
      "title": "Uncertainty-Aware Vision-based Risk Object Identification via Conformal Risk Tube Prediction",
      "authors": [
        "Kai-Yu Fu",
        "Yi-Ting Chen"
      ],
      "primary_subject": "Computer Vision and Pattern Recognition (cs.CV)",
      "subject_categories": [
        "cs.CV"
      ],
      "announcement_date": "2026-03-26"
    },
    {
      "paper_id": "2603.23916",
      "abs_url": "https://arxiv.org/abs/2603.23916",
      "source_category": "cs.CV",
      "title": "DecepGPT: Schema-Driven Deception Detection with Multicultural Datasets and Robust Multimodal Learning",
      "authors": [
        "Jiajian Huang",
        "Dongliang Zhu",
        "Zitong YU",
        "Hui Ma",
        "Jiayu Zhang",
        "Chunmei Zhu",
        "Xiaochun Cao"
      ],
      "primary_subject": "Computer Vision and Pattern Recognition (cs.CV)",
      "subject_categories": [
        "cs.AI",
        "cs.CV"
      ],
      "announcement_date": "2026-03-26"
    },
    {
      "paper_id": "2603.23914",
      "abs_url": "https://arxiv.org/abs/2603.23914",
      "source_category": "cs.CV",
      "title": "Attention-aware Inference Optimizations for Large Vision-Language Models with Memory-efficient Decoding",
      "authors": [
        "Fatih Ilhan",
        "Gaowen Liu",
        "Ramana Rao Kompella",
        "Selim Furkan Tekin",
        "Tiansheng Huang",
        "Zachary Yahn",
        "Yichang Xu",
        "Ling Liu"
      ],
      "primary_subject": "Computer Vision and Pattern Recognition (cs.CV)",
      "subject_categories": [
        "cs.CV",
        "cs.LG"
      ],
      "announcement_date": "2026-03-26"
    },
    {
      "paper_id": "2603.23906",
      "abs_url": "https://arxiv.org/abs/2603.23906",
      "source_category": "cs.CV",
      "title": "GenMask: Adapting DiT for Segmentation via Direct Mask Generation",
      "authors": [
        "Yuhuan Yang",
        "Xianwei Zhuang",
        "Yuxuan Cai",
        "Chaofan Ma",
        "Shuai Bai",
        "Jiangchao Yao",
        "Ya Zhang",
        "Junyang Lin",
        "Yanfeng Wang"
      ],
      "primary_subject": "Computer Vision and Pattern Recognition (cs.CV)",
      "subject_categories": [
        "cs.CV"
      ],
      "announcement_date": "2026-03-26"
    },
    {
      "paper_id": "2603.23903",
      "abs_url": "https://arxiv.org/abs/2603.23903",
      "source_category": "cs.CV",
      "title": "Latent Bias Alignment for High-Fidelity Diffusion Inversion in Real-World Image Reconstruction and Manipulation",
      "authors": [
        "Weiming Chen",
        "Qifan Liu",
        "Siyi Liu",
        "Yushun Tang",
        "Yijia Wang",
        "Zhihan Zhu",
        "Zhihai He"
      ],
      "primary_subject": "Computer Vision and Pattern Recognition (cs.CV)",
      "subject_categories": [
        "cs.AI",
        "cs.CV"
      ],
      "announcement_date": "2026-03-26"
    },
    {
      "paper_id": "2603.23902",
      "abs_url": "https://arxiv.org/abs/2603.23902",
      "source_category": "cs.CV",
      "title": "Knowledge-Refined Dual Context-Aware Network for Partially Relevant Video Retrieval",
      "authors": [
        "Junkai Yang",
        "Qirui Wang",
        "Yaoqing Jin",
        "Shuai Ma",
        "Minghan Xu",
        "Shanmin Pang"
      ],
      "primary_subject": "Computer Vision and Pattern Recognition (cs.CV)",
      "subject_categories": [
        "cs.AI",
        "cs.CV"
      ],
      "announcement_date": "2026-03-26"
    },
    {
      "paper_id": "2603.23896",
      "abs_url": "https://arxiv.org/abs/2603.23896",
      "source_category": "cs.CV",
      "title": "MMTIT-Bench: A Multilingual and Multi-Scenario Benchmark with Cognition-Perception-Reasoning Guided Text-Image Machine Translation",
      "authors": [
        "Gengluo Li",
        "Chengquan Zhang",
        "Yupu Liang",
        "Huawen Shen",
        "Yaping Zhang",
        "Pengyuan Lyu",
        "Weinong Wang",
        "Xingyu Wan",
        "Gangyan Zeng",
        "Han Hu",
        "Can Ma",
        "Yu Zhou"
      ],
      "primary_subject": "Computer Vision and Pattern Recognition (cs.CV)",
      "subject_categories": [
        "cs.CV"
      ],
      "announcement_date": "2026-03-26"
    },
    {
      "paper_id": "2603.23891",
      "abs_url": "https://arxiv.org/abs/2603.23891",
      "source_category": "cs.CV",
      "title": "FilterGS: Traversal-Free Parallel Filtering and Adaptive Shrinking for Large-Scale LoD 3D Gaussian Splatting",
      "authors": [
        "Yixian Wang",
        "Haolin Yu",
        "Jiadong Tang",
        "Yu Gao",
        "Xihan Wang",
        "Yufeng Yue",
        "Yi Yang"
      ],
      "primary_subject": "Computer Vision and Pattern Recognition (cs.CV)",
      "subject_categories": [
        "cs.CV"
      ],
      "announcement_date": "2026-03-26"
    },
    {
      "paper_id": "2603.23885",
      "abs_url": "https://arxiv.org/abs/2603.23885",
      "source_category": "cs.CV",
      "title": "Towards Real-World Document Parsing via Realistic Scene Synthesis and Document-Aware Training",
      "authors": [
        "Gengluo Li",
        "Chengquan Zhang",
        "Yupu Liang",
        "Huawen Shen",
        "Yaping Zhang",
        "Pengyuan Lyu",
        "Weinong Wang",
        "Xingyu Wan",
        "Gangyan Zeng",
        "Han Hu",
        "Can Ma",
        "Yu Zhou"
      ],
      "primary_subject": "Computer Vision and Pattern Recognition (cs.CV)",
      "subject_categories": [
        "cs.CV"
      ],
      "announcement_date": "2026-03-26"
    },
    {
      "paper_id": "2603.23883",
      "abs_url": "https://arxiv.org/abs/2603.23883",
      "source_category": "cs.CV",
      "title": "BioVITA: Biological Dataset, Model, and Benchmark for Visual-Textual-Acoustic Alignment",
      "authors": [
        "Risa Shinoda",
        "Kaede Shiohara",
        "Nakamasa Inoue",
        "Kuniaki Saito",
        "Hiroaki Santo",
        "Fumio Okura"
      ],
      "primary_subject": "Computer Vision and Pattern Recognition (cs.CV)",
      "subject_categories": [
        "cs.CV"
      ],
      "announcement_date": "2026-03-26"
    },
    {
      "paper_id": "2603.23874",
      "abs_url": "https://arxiv.org/abs/2603.23874",
      "source_category": "cs.CV",
      "title": "EnvSocial-Diff: A Diffusion-Based Crowd Simulation Model with Environmental Conditioning and Individual-Group Interaction",
      "authors": [
        "Bingxue Zhao",
        "Qi Zhang",
        "Hui Huang"
      ],
      "primary_subject": "Computer Vision and Pattern Recognition (cs.CV)",
      "subject_categories": [
        "cs.CV"
      ],
      "announcement_date": "2026-03-26"
    },
    {
      "paper_id": "2603.23868",
      "abs_url": "https://arxiv.org/abs/2603.23868",
      "source_category": "cs.CV",
      "title": "MLE-UVAD: Minimal Latent Entropy Autoencoder for Fully Unsupervised Video Anomaly Detection",
      "authors": [
        "Yuang Geng",
        "Junkai Zhou",
        "Kang Yang",
        "Pan He",
        "Zhuoyang Zhou",
        "Jose C. Principe",
        "Joel Harley",
        "Ivan Ruchkin"
      ],
      "primary_subject": "Computer Vision and Pattern Recognition (cs.CV)",
      "subject_categories": [
        "cs.CV"
      ],
      "announcement_date": "2026-03-26"
    },
    {
      "paper_id": "2603.23864",
      "abs_url": "https://arxiv.org/abs/2603.23864",
      "source_category": "cs.CV",
      "title": "See, Remember, Explore: A Benchmark and Baselines for Streaming Spatial Reasoning",
      "authors": [
        "Yuxi Wei",
        "Wei Huang",
        "Qirui Chen",
        "Lu Hou",
        "Xiaojuan Qi"
      ],
      "primary_subject": "Computer Vision and Pattern Recognition (cs.CV)",
      "subject_categories": [
        "cs.CV"
      ],
      "announcement_date": "2026-03-26"
    },
    {
      "paper_id": "2603.23845",
      "abs_url": "https://arxiv.org/abs/2603.23845",
      "source_category": "cs.CV",
      "title": "3D-LLDM: Label-Guided 3D Latent Diffusion Model for Improving High-Resolution Synthetic MR Imaging in Hepatic Structure Segmentation",
      "authors": [
        "Kyeonghun Kim",
        "Jaehyeok Bae",
        "Youngung Han",
        "Joo Young Bae",
        "Seoyoung Ju",
        "Junsu Lim",
        "Gyeongmin Kim",
        "Nam-Joon Kim",
        "Woo Kyoung Jeong",
        "Ken Ying-Kai Liao",
        "Won Jae Lee",
        "Pa Hong",
        "Hyuk-Jae Lee"
      ],
      "primary_subject": "Computer Vision and Pattern Recognition (cs.CV)",
      "subject_categories": [
        "cs.CV"
      ],
      "announcement_date": "2026-03-26"
    },
    {
      "paper_id": "2603.23794",
      "abs_url": "https://arxiv.org/abs/2603.23794",
      "source_category": "cs.CV",
      "title": "Sparse Autoencoders for Interpretable Medical Image Representation Learning",
      "authors": [
        "Philipp Wesp",
        "Robbie Holland",
        "Vasiliki Sideri-Lampretsa",
        "Sergios Gatidis"
      ],
      "primary_subject": "Computer Vision and Pattern Recognition (cs.CV)",
      "subject_categories": [
        "cs.CV",
        "cs.LG"
      ],
      "announcement_date": "2026-03-26"
    },
    {
      "paper_id": "2603.23788",
      "abs_url": "https://arxiv.org/abs/2603.23788",
      "source_category": "cs.CV",
      "title": "Re-Prompting SAM 3 via Object Retrieval: 3rd of the 5th PVUW MOSE Track",
      "authors": [
        "Mingqi Gao",
        "Sijie Li",
        "Jungong Han"
      ],
      "primary_subject": "Computer Vision and Pattern Recognition (cs.CV)",
      "subject_categories": [
        "cs.CV"
      ],
      "announcement_date": "2026-03-26"
    },
    {
      "paper_id": "2603.23785",
      "abs_url": "https://arxiv.org/abs/2603.23785",
      "source_category": "cs.CV",
      "title": "Retinal Disease Classification from Fundus Images using CNN Transfer Learning",
      "authors": [
        "Ali Akram"
      ],
      "primary_subject": "Computer Vision and Pattern Recognition (cs.CV)",
      "subject_categories": [
        "cs.CV",
        "cs.LG"
      ],
      "announcement_date": "2026-03-26"
    },
    {
      "paper_id": "2603.23766",
      "abs_url": "https://arxiv.org/abs/2603.23766",
      "source_category": "cs.CV",
      "title": "Semantic Iterative Reconstruction: One-Shot Universal Anomaly Detection",
      "authors": [
        "Ning Zhu"
      ],
      "primary_subject": "Computer Vision and Pattern Recognition (cs.CV)",
      "subject_categories": [
        "cs.CV"
      ],
      "announcement_date": "2026-03-26"
    },
    {
      "paper_id": "2603.23757",
      "abs_url": "https://arxiv.org/abs/2603.23757",
      "source_category": "cs.CV",
      "title": "Learning Cross-Joint Attention for Generalizable Video-Based Seizure Detection",
      "authors": [
        "Omar Zamzam",
        "Takfarinas Medani",
        "Chinmay Chinara",
        "Richard Leahy"
      ],
      "primary_subject": "Computer Vision and Pattern Recognition (cs.CV)",
      "subject_categories": [
        "cs.CV"
      ],
      "announcement_date": "2026-03-26"
    },
    {
      "paper_id": "2603.23754",
      "abs_url": "https://arxiv.org/abs/2603.23754",
      "source_category": "cs.CV",
      "title": "IJmond Industrial Smoke Segmentation Dataset",
      "authors": [
        "Yen-Chia Hsu",
        "Despoina Touska"
      ],
      "primary_subject": "Computer Vision and Pattern Recognition (cs.CV)",
      "subject_categories": [
        "cs.CV"
      ],
      "announcement_date": "2026-03-26"
    },
    {
      "paper_id": "2603.23742",
      "abs_url": "https://arxiv.org/abs/2603.23742",
      "source_category": "cs.CV",
      "title": "Detection and Classification of (Pre)Cancerous Cells in Pap Smears: An Ensemble Strategy for the RIVA Cervical Cytology Challenge",
      "authors": [
        "Lautaro Kogan",
        "María Victoria Ríos"
      ],
      "primary_subject": "Computer Vision and Pattern Recognition (cs.CV)",
      "subject_categories": [
        "cs.CV"
      ],
      "announcement_date": "2026-03-26"
    },
    {
      "paper_id": "2603.23730",
      "abs_url": "https://arxiv.org/abs/2603.23730",
      "source_category": "cs.CV",
      "title": "An Adapter-free Fine-tuning Approach for Tuning 3D Foundation Models",
      "authors": [
        "Sneha Paul",
        "Zachary Patterson",
        "Nizar Bouguila"
      ],
      "primary_subject": "Computer Vision and Pattern Recognition (cs.CV)",
      "subject_categories": [
        "cs.CV"
      ],
      "announcement_date": "2026-03-26"
    },
    {
      "paper_id": "2603.23729",
      "abs_url": "https://arxiv.org/abs/2603.23729",
      "source_category": "cs.CV",
      "title": "Bi-CRCL: Bidirectional Conservative-Radical Complementary Learning with Pre-trained Foundation Models for Class-incremental Medical Image Analysis",
      "authors": [
        "Xinyao Wu",
        "Zhe Xu",
        "Cheng Chen",
        "Jiawei Ma",
        "Yefeng Zheng",
        "Raymond Kai-yu Tong"
      ],
      "primary_subject": "Computer Vision and Pattern Recognition (cs.CV)",
      "subject_categories": [
        "cs.CV"
      ],
      "announcement_date": "2026-03-26"
    },
    {
      "paper_id": "2603.23711",
      "abs_url": "https://arxiv.org/abs/2603.23711",
      "source_category": "cs.CV",
      "title": "Mind the Hitch: Dynamic Calibration and Articulated Perception for Autonomous Trucks",
      "authors": [
        "Morui Zhu",
        "Yongqi Zhu",
        "Song Fu",
        "Qing Yang"
      ],
      "primary_subject": "Computer Vision and Pattern Recognition (cs.CV)",
      "subject_categories": [
        "cs.CV"
      ],
      "announcement_date": "2026-03-26"
    },
    {
      "paper_id": "2603.23694",
      "abs_url": "https://arxiv.org/abs/2603.23694",
      "source_category": "cs.CV",
      "title": "CoRe: Joint Optimization with Contrastive Learning for Medical Image Registration",
      "authors": [
        "Eytan Kats",
        "Christoph Grossbroehmer",
        "Ziad Al-Haj Hemidi",
        "Fenja Falta",
        "Wiebke Heyer",
        "Mattias P. Heinrich"
      ],
      "primary_subject": "Computer Vision and Pattern Recognition (cs.CV)",
      "subject_categories": [
        "cs.CV"
      ],
      "announcement_date": "2026-03-26"
    },
    {
      "paper_id": "2603.23686",
      "abs_url": "https://arxiv.org/abs/2603.23686",
      "source_category": "cs.CV",
      "title": "AdvSplat: Adversarial Attacks on Feed-Forward Gaussian Splatting Models",
      "authors": [
        "Yiran Qiao",
        "Yiren Lu",
        "Yunlai Zhou",
        "Rui Yang",
        "Linlin Hou",
        "Yu Yin",
        "Jing Ma"
      ],
      "primary_subject": "Computer Vision and Pattern Recognition (cs.CV)",
      "subject_categories": [
        "cs.CV"
      ],
      "announcement_date": "2026-03-26"
    },
    {
      "paper_id": "2603.23684",
      "abs_url": "https://arxiv.org/abs/2603.23684",
      "source_category": "cs.CV",
      "title": "MoCHA: Denoising Caption Supervision for Motion-Text Retrieval",
      "authors": [
        "Nikolai Warner",
        "Cameron Ethan Taylor",
        "Irfan Essa",
        "Apaar Sadhwani"
      ],
      "primary_subject": "Computer Vision and Pattern Recognition (cs.CV)",
      "subject_categories": [
        "cs.CV"
      ],
      "announcement_date": "2026-03-26"
    },
    {
      "paper_id": "2603.23677",
      "abs_url": "https://arxiv.org/abs/2603.23677",
      "source_category": "cs.CV",
      "title": "Prototype Fusion: A Training-Free Multi-Layer Approach to OOD Detection",
      "authors": [
        "Shreen Gul",
        "Mohamed Elmahallawy",
        "Ardhendu Tripathy",
        "Sanjay Madria"
      ],
      "primary_subject": "Computer Vision and Pattern Recognition (cs.CV)",
      "subject_categories": [
        "cs.AI",
        "cs.CV"
      ],
      "announcement_date": "2026-03-26"
    },
    {
      "paper_id": "2603.23669",
      "abs_url": "https://arxiv.org/abs/2603.23669",
      "source_category": "cs.CV",
      "title": "Estimating Individual Tree Height and Species from UAV Imagery",
      "authors": [
        "Jannik Endres",
        "Etienne Laliberté",
        "David Rolnick",
        "Arthur Ouaknine"
      ],
      "primary_subject": "Computer Vision and Pattern Recognition (cs.CV)",
      "subject_categories": [
        "cs.AI",
        "cs.CV",
        "cs.LG"
      ],
      "announcement_date": "2026-03-26"
    },
    {
      "paper_id": "2603.23650",
      "abs_url": "https://arxiv.org/abs/2603.23650",
      "source_category": "cs.CV",
      "title": "Foundation Model Embeddings Meet Blended Emotions: A Multimodal Fusion Approach for the BLEMORE Challenge",
      "authors": [
        "Masoumeh Chapariniya",
        "Aref Farhadipour",
        "Sarah Ebling",
        "Volker Dellwo",
        "Teodora Vukovic"
      ],
      "primary_subject": "Computer Vision and Pattern Recognition (cs.CV)",
      "subject_categories": [
        "cs.CV"
      ],
      "announcement_date": "2026-03-26"
    },
    {
      "paper_id": "2603.23647",
      "abs_url": "https://arxiv.org/abs/2603.23647",
      "source_category": "cs.CV",
      "title": "λSplit: Self-Supervised Content-Aware Spectral Unmixing for Fluorescence Microscopy",
      "authors": [
        "Federico Carrara",
        "Talley Lambert",
        "Mehdi Seifi",
        "Florian Jug"
      ],
      "primary_subject": "Computer Vision and Pattern Recognition (cs.CV)",
      "subject_categories": [
        "cs.AI",
        "cs.CV",
        "cs.LG"
      ],
      "announcement_date": "2026-03-26"
    },
    {
      "paper_id": "2603.23637",
      "abs_url": "https://arxiv.org/abs/2603.23637",
      "source_category": "cs.CV",
      "title": "Stochastic Ray Tracing for the Reconstruction of 3D Gaussian Splatting",
      "authors": [
        "Peiyu Xu",
        "Xin Sun",
        "Krishna Mullia",
        "Raymond Fei",
        "Iliyan Georgiev",
        "Shuang Zhao"
      ],
      "primary_subject": "Computer Vision and Pattern Recognition (cs.CV)",
      "subject_categories": [
        "cs.CV"
      ],
      "announcement_date": "2026-03-26"
    },
    {
      "paper_id": "2603.23627",
      "abs_url": "https://arxiv.org/abs/2603.23627",
      "source_category": "cs.CV",
      "title": "Ukrainian Visual Word Sense Disambiguation Benchmark",
      "authors": [
        "Yurii Laba",
        "Yaryna Mohytych",
        "Ivanna Rohulia",
        "Halyna Kyryleyza",
        "Hanna Dydyk-Meush",
        "Oles Dobosevych",
        "Rostyslav Hryniv"
      ],
      "primary_subject": "Computer Vision and Pattern Recognition (cs.CV)",
      "subject_categories": [
        "cs.AI",
        "cs.CV"
      ],
      "announcement_date": "2026-03-26"
    },
    {
      "paper_id": "2603.23617",
      "abs_url": "https://arxiv.org/abs/2603.23617",
      "source_category": "cs.CV",
      "title": "M3T: Discrete Multi-Modal Motion Tokens for Sign Language Production",
      "authors": [
        "Alexandre Symeonidis-Herzig",
        "Jianhe Low",
        "Ozge Mercanoglu Sincan",
        "Richard Bowden"
      ],
      "primary_subject": "Computer Vision and Pattern Recognition (cs.CV)",
      "subject_categories": [
        "cs.CV"
      ],
      "announcement_date": "2026-03-26"
    },
    {
      "paper_id": "2603.23607",
      "abs_url": "https://arxiv.org/abs/2603.23607",
      "source_category": "cs.CV",
      "title": "LongTail Driving Scenarios with Reasoning Traces: The KITScenes LongTail Dataset",
      "authors": [
        "Royden Wagner",
        "Omer Sahin Tas",
        "Jaime Villa",
        "Felix Hauser",
        "Yinzhe Shen",
        "Marlon Steiner",
        "Dominik Strutz",
        "Carlos Fernandez",
        "Christian Kinzig",
        "Guillermo S. Guitierrez-Cabello",
        "Hendrik Königshof",
        "Fabian Immel",
        "Richard Schwarzkopf",
        "Nils Alexander Rack",
        "Kevin Rösch",
        "Kaiwen Wang",
        "Jan-Hendrik Pauls",
        "Martin Lauer",
        "Igor Gilitschenski",
        "Holger Caesar",
        "Christoph Stiller"
      ],
      "primary_subject": "Computer Vision and Pattern Recognition (cs.CV)",
      "subject_categories": [
        "cs.CV",
        "cs.RO"
      ],
      "announcement_date": "2026-03-26"
    },
    {
      "paper_id": "2603.24576",
      "abs_url": "https://arxiv.org/abs/2603.24576",
      "source_category": "cs.CV",
      "title": "Chameleon: Episodic Memory for Long-Horizon Robotic Manipulation",
      "authors": [
        "Xinying Guo",
        "Chenxi Jiang",
        "Hyun Bin Kim",
        "Ying Sun",
        "Yang Xiao",
        "Yuhang Han",
        "Jianfei Yang"
      ],
      "primary_subject": "Robotics (cs.RO)",
      "subject_categories": [
        "cs.AI",
        "cs.CV",
        "cs.RO"
      ],
      "announcement_date": "2026-03-26"
    },
    {
      "paper_id": "2603.24549",
      "abs_url": "https://arxiv.org/abs/2603.24549",
      "source_category": "cs.CV",
      "title": "A Sociolinguistic Analysis of Automatic Speech Recognition Bias in Newcastle English",
      "authors": [
        "Dana Serditova",
        "Kevin Tang"
      ],
      "primary_subject": "Computation and Language (cs.CL)",
      "subject_categories": [
        "cs.AI",
        "cs.CL",
        "cs.CV",
        "cs.SD"
      ],
      "announcement_date": "2026-03-26"
    },
    {
      "paper_id": "2603.24533",
      "abs_url": "https://arxiv.org/abs/2603.24533",
      "source_category": "cs.CV",
      "title": "UI-Voyager: A Self-Evolving GUI Agent Learning via Failed Experience",
      "authors": [
        "Zichuan Lin",
        "Feiyu Liu",
        "Yijun Yang",
        "Jiafei Lyu",
        "Yiming Gao",
        "Yicheng Liu",
        "Zhicong Lu",
        "Yangbin Yu",
        "Mingyu Yang",
        "Junyou Li",
        "Deheng Ye",
        "Jie Jiang"
      ],
      "primary_subject": "Machine Learning (cs.LG)",
      "subject_categories": [
        "cs.AI",
        "cs.CV",
        "cs.LG"
      ],
      "announcement_date": "2026-03-26"
    },
    {
      "paper_id": "2603.24440",
      "abs_url": "https://arxiv.org/abs/2603.24440",
      "source_category": "cs.CV",
      "title": "CUA-Suite: Massive Human-annotated Video Demonstrations for Computer-Use Agents",
      "authors": [
        "Xiangru Jian",
        "Shravan Nayak",
        "Kevin Qinghong Lin",
        "Aarash Feizi",
        "Kaixin Li",
        "Patrice Bechard",
        "Spandana Gella",
        "Sai Rajeswar"
      ],
      "primary_subject": "Machine Learning (cs.LG)",
      "subject_categories": [
        "cs.AI",
        "cs.CV",
        "cs.LG"
      ],
      "announcement_date": "2026-03-26"
    },
    {
      "paper_id": "2603.24329",
      "abs_url": "https://arxiv.org/abs/2603.24329",
      "source_category": "cs.CV",
      "title": "GameplayQA: A Benchmarking Framework for Decision-Dense POV-Synced Multi-Video Understanding of 3D Virtual Agents",
      "authors": [
        "Yunzhe Wang",
        "Runhui Xu",
        "Kexin Zheng",
        "Tianyi Zhang",
        "Jayavibhav Niranjan Kogundi",
        "Soham Hans",
        "Volkan Ustun"
      ],
      "primary_subject": "Computation and Language (cs.CL)",
      "subject_categories": [
        "cs.AI",
        "cs.CL",
        "cs.CV"
      ],
      "announcement_date": "2026-03-26"
    },
    {
      "paper_id": "2603.24232",
      "abs_url": "https://arxiv.org/abs/2603.24232",
      "source_category": "cs.CV",
      "title": "Attack Assessment and Augmented Identity Recognition for Human Skeleton Data",
      "authors": [
        "Joseph G. Zalameda",
        "Megan A. Witherow",
        "Alexander M. Glandon",
        "Jose Aguilera",
        "Khan M. Iftekharuddin"
      ],
      "primary_subject": "Machine Learning (cs.LG)",
      "subject_categories": [
        "cs.CR",
        "cs.CV",
        "cs.LG"
      ],
      "announcement_date": "2026-03-26"
    },
    {
      "paper_id": "2603.24176",
      "abs_url": "https://arxiv.org/abs/2603.24176",
      "source_category": "cs.CV",
      "title": "Modeling Spatiotemporal Neural Frames for High Resolution Brain Dynamic",
      "authors": [
        "Wanying Qu",
        "Jianxiong Gao",
        "Wei Wang",
        "Yanwei Fu"
      ],
      "primary_subject": "Image and Video Processing (eess.IV)",
      "subject_categories": [
        "cs.CV",
        "eess.IV",
        "q-bio.NC"
      ],
      "announcement_date": "2026-03-26"
    },
    {
      "paper_id": "2603.24131",
      "abs_url": "https://arxiv.org/abs/2603.24131",
      "source_category": "cs.CV",
      "title": "Reservoir-Based Graph Convolutional Networks",
      "authors": [
        "Mayssa Soussia",
        "Gita Ayu Salsabila",
        "Mohamed Ali Mahjoub",
        "Islem Rekik"
      ],
      "primary_subject": "Machine Learning (cs.LG)",
      "subject_categories": [
        "cs.CV",
        "cs.LG"
      ],
      "announcement_date": "2026-03-26"
    },
    {
      "paper_id": "2603.24109",
      "abs_url": "https://arxiv.org/abs/2603.24109",
      "source_category": "cs.CV",
      "title": "Comparative analysis of dual-form networks for live land monitoring using multi-modal satellite image time series",
      "authors": [
        "Iris Dumeur",
        "Jérémy Anger",
        "Gabriele Facciolo"
      ],
      "primary_subject": "Image and Video Processing (eess.IV)",
      "subject_categories": [
        "cs.AI",
        "cs.CV",
        "eess.IV"
      ],
      "announcement_date": "2026-03-26"
    },
    {
      "paper_id": "2603.23974",
      "abs_url": "https://arxiv.org/abs/2603.23974",
      "source_category": "cs.CV",
      "title": "Machine vision with small numbers of detected photons per inference",
      "authors": [
        "Shi-Yuan Ma",
        "Jérémie Laydevant",
        "Mandar M. Sohoni",
        "Logan G. Wright",
        "Tianyu Wang",
        "Peter L. McMahon"
      ],
      "primary_subject": "Optics (physics.optics)",
      "subject_categories": [
        "cs.CV",
        "cs.ET",
        "cs.LG"
      ],
      "announcement_date": "2026-03-26"
    },
    {
      "paper_id": "2603.23961",
      "abs_url": "https://arxiv.org/abs/2603.23961",
      "source_category": "cs.CV",
      "title": "GRMLR: Knowledge-Enhanced Small-Data Learning for Deep-Sea Cold Seep Stage Inference",
      "authors": [
        "Chenxu Zhou",
        "Zelin Liu",
        "Rui Cai",
        "Houlin Gong",
        "Yikang Yu",
        "Jia Zeng",
        "Yanru Pei",
        "Liang Zhang",
        "Weishu Zhao",
        "Xiaofeng Gao"
      ],
      "primary_subject": "Machine Learning (cs.LG)",
      "subject_categories": [
        "cs.CV",
        "cs.LG"
      ],
      "announcement_date": "2026-03-26"
    },
    {
      "paper_id": "2603.23933",
      "abs_url": "https://arxiv.org/abs/2603.23933",
      "source_category": "cs.CV",
      "title": "ORACLE: Orchestrate NPC Daily Activities using Contrastive Learning with Transformer-CVAE",
      "authors": [
        "Seong-Eun Hong",
        "JuYeong Hwang",
        "RyunHa Lee",
        "HyeongYeop Kang"
      ],
      "primary_subject": "Graphics (cs.GR)",
      "subject_categories": [
        "cs.CL",
        "cs.CV",
        "cs.GR",
        "cs.LG"
      ],
      "announcement_date": "2026-03-26"
    },
    {
      "paper_id": "2603.23867",
      "abs_url": "https://arxiv.org/abs/2603.23867",
      "source_category": "cs.CV",
      "title": "Can VLMs Reason Robustly? A Neuro-Symbolic Investigation",
      "authors": [
        "Weixin Chen",
        "Antonio Vergari",
        "Han Zhao"
      ],
      "primary_subject": "Machine Learning (cs.LG)",
      "subject_categories": [
        "cs.AI",
        "cs.CV",
        "cs.LG"
      ],
      "announcement_date": "2026-03-26"
    },
    {
      "paper_id": "2603.23672",
      "abs_url": "https://arxiv.org/abs/2603.23672",
      "source_category": "cs.CV",
      "title": "Bio-Inspired Event-Based Visual Servoing for Ground Robots",
      "authors": [
        "Maral Mordad",
        "Kian Behzad",
        "Debojyoti Biswas",
        "Noah J. Cowan",
        "Milad Siami"
      ],
      "primary_subject": "Robotics (cs.RO)",
      "subject_categories": [
        "cs.CV",
        "cs.RO"
      ],
      "announcement_date": "2026-03-26"
    },
    {
      "paper_id": "2603.23559",
      "abs_url": "https://arxiv.org/abs/2603.23559",
      "source_category": "cs.CV",
      "title": "CAPTCHA Solving for Native GUI Agents: Automated Reasoning-Action Data Generation and Self-Corrective Training",
      "authors": [
        "Yuxi Chen",
        "Haoyu Zhai",
        "Chenkai Wang",
        "Rui Yang",
        "Lingming Zhang",
        "Gang Wang",
        "Huan Zhang"
      ],
      "primary_subject": "Cryptography and Security (cs.CR)",
      "subject_categories": [
        "cs.AI",
        "cs.CR",
        "cs.CV"
      ],
      "announcement_date": "2026-03-26"
    },
    {
      "paper_id": "2603.23521",
      "abs_url": "https://arxiv.org/abs/2603.23521",
      "source_category": "cs.CV",
      "title": "Chitrakshara: A Large Multilingual Multimodal Dataset for Indian languages",
      "authors": [
        "Shaharukh Khan",
        "Ali Faraz",
        "Abhinav Ravi",
        "Mohd Nauman",
        "Mohd Sarfraz",
        "Akshat Patidar",
        "Raja Kolla",
        "Chandra Khatri",
        "Shubham Agarwal"
      ],
      "primary_subject": "Computation and Language (cs.CL)",
      "subject_categories": [
        "cs.AI",
        "cs.CL",
        "cs.CV"
      ],
      "announcement_date": "2026-03-26"
    },
    {
      "paper_id": "2603.23511",
      "abs_url": "https://arxiv.org/abs/2603.23511",
      "source_category": "cs.CV",
      "title": "DISCO: Document Intelligence Suite for COmparative Evaluation",
      "authors": [
        "Kenza Benkirane",
        "Dan Goldwater",
        "Martin Asenov",
        "Aneiss Ghodsi"
      ],
      "primary_subject": "Computation and Language (cs.CL)",
      "subject_categories": [
        "cs.AI",
        "cs.CL",
        "cs.CV"
      ],
      "announcement_date": "2026-03-26"
    },
    {
      "paper_id": "2603.13528",
      "abs_url": "https://arxiv.org/abs/2603.13528",
      "source_category": "cs.CV",
      "title": "Learning Actionable Manipulation Recovery via Counterfactual Failure Synthesis",
      "authors": [
        "Dayou Li",
        "Jiuzhou Lei",
        "Hao Wang",
        "Lulin Liu",
        "Yunhao Yang",
        "Zihan Wang",
        "Bangya Liu",
        "Minghui Zheng",
        "Zhiwen Fan"
      ],
      "primary_subject": "Robotics (cs.RO)",
      "subject_categories": [
        "cs.CV",
        "cs.RO"
      ],
      "announcement_date": "2026-03-26"
    }
  ]
}